<?xml version="1.0" encoding="UTF-8"?>
<mods:mods xmlns:mods="http://www.loc.gov/mods/v3"
           xmlns:xlink="http://www.w3.org/1999/xlink"
           xmlns:xsi="http://www.w3.org/2001/XMLSchema-instance"
           version="3.5"
           xsi:schemaLocation="http://www.loc.gov/mods/v3 http://www.loc.gov/standards/mods/v3/mods-3-5.xsd">
   <mods:identifier type="local">0012_000192_000200_0000</mods:identifier>
   <mods:titleInfo>
      <mods:title>Letter, Watson B. Smith in Marysville E. Tenn. to his father, 1863 Nov. 5</mods:title>
   </mods:titleInfo>
   <mods:abstract>Watson B. Smith wrote to his father on Nov. 5, 1863 while serving in the Civil War. He mentioned the evacuation of Soudon (Loudon). Brig. Genl. Sanders offered Smith the position of Asst. Adjt. Genl. on his staff. Smith had been acting in this position, but had not received the rank and pay. He thought his uncle might be able to help him. It had the rank of Captain and was an appointment from the President. He sent his father a copy of the letter where Sanders had requested his appointment. He thought he was well suited for the position. Gen. White had given him a wonderful recommendation and would not release him to Sanders unless he got the rank of Captain/A.A.G. He told of capturing and killing the enemy near the Little Tennessee River. The union men were exposed to a sever fire from the rebels across the river, but nobody was killed or wounded, even though they lost two horses. They captured some officers. He sent his father an autograph of Col. Wolford. He liked Maryville. He apologized for not writing sooner due to trying to learn his new job and being short-staffed. He told his father he was well and in good spirits.</mods:abstract>
   <mods:originInfo>
      <mods:dateCreated>1863-11-05</mods:dateCreated>
      <mods:dateCreated encoding="edtf">1863-11-05</mods:dateCreated>
   </mods:originInfo>
   <mods:name>
      <mods:namePart>Smith, Watson B., d. 1881</mods:namePart>
      <mods:role>
         <mods:roleTerm authority="marcrelator"
                        authorityURI="http://id.loc.gov/vocabulary/relators/cre">Creator</mods:roleTerm>
      </mods:role>
   </mods:name>
   <mods:subject>
      <mods:topic>Soldiers -- Michigan -- Correspondence.</mods:topic>
   </mods:subject>
   <mods:subject>
      <mods:topic>Promotions, Military.</mods:topic>
   </mods:subject>
   <mods:subject>
      <mods:topic>War casualties.</mods:topic>
   </mods:subject>
   <mods:subject>
      <mods:topic>Tennessee -- History -- Civil War, 1861-1865.</mods:topic>
   </mods:subject>
   <mods:subject>
      <mods:topic>United States -- History -- Civil War, 1861-1865.</mods:topic>
   </mods:subject>
   <mods:subject>
      <mods:topic>Smith, Watson B., d. 1881 -- Correspondence.</mods:topic>
   </mods:subject>
   <mods:subject>
      <mods:topic>United States. Army. Michigan Cavalry Regiment, 8th (1862-1865).</mods:topic>
   </mods:subject>
   <mods:accessCondition type="use and reproduction"
                         xlink:href="http://rightsstatement.org/vocab/CNE/1.0/">Copyright Not Evaluated</mods:accessCondition>
   <mods:location>
      <mods:physicalLocation>University of Tennessee Knoxville. Libraries</mods:physicalLocation>
   </mods:location>
   <mods:relatedItem displayLabel="Project" type="host">
      <mods:titleInfo>
         <mods:title/>
      </mods:titleInfo>
   </mods:relatedItem>
   <mods:relatedItem displayLabel="Collection" type="host">
      <mods:titleInfo>
         <mods:title>Watson B. Smith Letter</mods:title>
      </mods:titleInfo>
   </mods:relatedItem>
   <mods:typeOfResource>text</mods:typeOfResource>
   <mods:language>
      <mods:languageTerm type="text" authority="iso639-2b">English</mods:languageTerm>
   </mods:language>
   <mods:recordInfo>
      <mods:recordContentSource>University of Tennessee Knoxville. Libraries</mods:recordContentSource>
      <mods:languageOfCataloging>
         <mods:languageTerm type="code" authority="iso639-2b">eng</mods:languageTerm>
      </mods:languageOfCataloging>
      <mods:recordCreationDate>2020-04-21-04:00</mods:recordCreationDate>
      <mods:recordOrigin>This MODS record was generated into MODS v3.5 from the TEI teiHeader by
          University of Tennessee Libraries Digital Initiatives, using a stylesheet available at
          https://github.com/utkdigitalinitiatives/tei-to-mods.</mods:recordOrigin>
   </mods:recordInfo>
</mods:mods>
